CHANGELOG.txt
LICENCE.txt
MANIFEST.in
README.txt
setup.py
nmuzb/__init__.py
nmuzb/maening.py
nmuzb.egg-info/PKG-INFO
nmuzb.egg-info/SOURCES.txt
nmuzb.egg-info/dependency_links.txt
nmuzb.egg-info/top_level.txt
venv/Lib/site-packages/_virtualenv.py
venv/Lib/site-packages/six.py
venv/Lib/site-packages/Pygments-2.15.1.dist-info/entry_points.txt
venv/Lib/site-packages/Pygments-2.15.1.dist-info/top_level.txt
venv/Lib/site-packages/_distutils_hack/__init__.py
venv/Lib/site-packages/_distutils_hack/override.py
venv/Lib/site-packages/bleach/__init__.py
venv/Lib/site-packages/bleach/callbacks.py
venv/Lib/site-packages/bleach/css_sanitizer.py
venv/Lib/site-packages/bleach/html5lib_shim.py
venv/Lib/site-packages/bleach/linkifier.py
venv/Lib/site-packages/bleach/parse_shim.py
venv/Lib/site-packages/bleach/sanitizer.py
venv/Lib/site-packages/bleach-6.0.0.dist-info/top_level.txt
venv/Lib/site-packages/bleach/_vendor/__init__.py
venv/Lib/site-packages/bleach/_vendor/parse.py
venv/Lib/site-packages/bleach/_vendor/vendor.txt
venv/Lib/site-packages/bleach/_vendor/html5lib/__init__.py
venv/Lib/site-packages/bleach/_vendor/html5lib/_ihatexml.py
venv/Lib/site-packages/bleach/_vendor/html5lib/_inputstream.py
venv/Lib/site-packages/bleach/_vendor/html5lib/_tokenizer.py
venv/Lib/site-packages/bleach/_vendor/html5lib/_utils.py
venv/Lib/site-packages/bleach/_vendor/html5lib/constants.py
venv/Lib/site-packages/bleach/_vendor/html5lib/html5parser.py
venv/Lib/site-packages/bleach/_vendor/html5lib/serializer.py
venv/Lib/site-packages/bleach/_vendor/html5lib-1.1.dist-info/top_level.txt
venv/Lib/site-packages/bleach/_vendor/html5lib/_trie/__init__.py
venv/Lib/site-packages/bleach/_vendor/html5lib/_trie/_base.py
venv/Lib/site-packages/bleach/_vendor/html5lib/_trie/py.py
venv/Lib/site-packages/bleach/_vendor/html5lib/filters/__init__.py
venv/Lib/site-packages/bleach/_vendor/html5lib/filters/alphabeticalattributes.py
venv/Lib/site-packages/bleach/_vendor/html5lib/filters/base.py
venv/Lib/site-packages/bleach/_vendor/html5lib/filters/inject_meta_charset.py
venv/Lib/site-packages/bleach/_vendor/html5lib/filters/lint.py
venv/Lib/site-packages/bleach/_vendor/html5lib/filters/optionaltags.py
venv/Lib/site-packages/bleach/_vendor/html5lib/filters/sanitizer.py
venv/Lib/site-packages/bleach/_vendor/html5lib/filters/whitespace.py
venv/Lib/site-packages/certifi-2023.5.7.dist-info/top_level.txt
venv/Lib/site-packages/charset_normalizer-3.1.0.dist-info/entry_points.txt
venv/Lib/site-packages/charset_normalizer-3.1.0.dist-info/top_level.txt
venv/Lib/site-packages/docutils-0.20.1.dist-info/COPYING.txt
venv/Lib/site-packages/docutils-0.20.1.dist-info/entry_points.txt
venv/Lib/site-packages/docutils-0.20.1.dist-info/top_level.txt
venv/Lib/site-packages/importlib_metadata-6.7.0.dist-info/top_level.txt
venv/Lib/site-packages/jaraco.classes-3.2.3.dist-info/top_level.txt
venv/Lib/site-packages/keyring-24.2.0.dist-info/entry_points.txt
venv/Lib/site-packages/keyring-24.2.0.dist-info/top_level.txt
venv/Lib/site-packages/markdown_it_py-3.0.0.dist-info/entry_points.txt
venv/Lib/site-packages/pip-23.1.2.dist-info/AUTHORS.txt
venv/Lib/site-packages/pip-23.1.2.dist-info/LICENSE.txt
venv/Lib/site-packages/pip-23.1.2.dist-info/entry_points.txt
venv/Lib/site-packages/pip-23.1.2.dist-info/top_level.txt
venv/Lib/site-packages/pkginfo-1.9.6.dist-info/LICENSE.txt
venv/Lib/site-packages/pkginfo-1.9.6.dist-info/entry_points.txt
venv/Lib/site-packages/pkginfo-1.9.6.dist-info/top_level.txt
venv/Lib/site-packages/pywin32_ctypes-0.2.1.dist-info/LICENSE.txt
venv/Lib/site-packages/pywin32_ctypes-0.2.1.dist-info/top_level.txt
venv/Lib/site-packages/readme_renderer-40.0.dist-info/top_level.txt
venv/Lib/site-packages/requests-2.31.0.dist-info/top_level.txt
venv/Lib/site-packages/requests_toolbelt-1.0.0.dist-info/top_level.txt
venv/Lib/site-packages/rfc3986-2.0.0.dist-info/top_level.txt
venv/Lib/site-packages/setuptools-67.8.0.dist-info/entry_points.txt
venv/Lib/site-packages/setuptools-67.8.0.dist-info/top_level.txt
venv/Lib/site-packages/six-1.16.0.dist-info/top_level.txt
venv/Lib/site-packages/twine-4.0.2.dist-info/entry_points.txt
venv/Lib/site-packages/twine-4.0.2.dist-info/top_level.txt
venv/Lib/site-packages/urllib3-2.0.3.dist-info/licenses/LICENSE.txt
venv/Lib/site-packages/webencodings-0.5.1.dist-info/top_level.txt
venv/Lib/site-packages/wheel-0.40.0.dist-info/LICENSE.txt
venv/Lib/site-packages/wheel-0.40.0.dist-info/entry_points.txt
venv/Lib/site-packages/zipp-3.15.0.dist-info/top_level.txt
